audioplayer/__init__.py
audioplayer/abstractaudioplayer.py
audioplayer/audioplayer_linux.py
audioplayer/audioplayer_macos.py
audioplayer/audioplayer_windows.py
audioplayer-0.6.dist-info/LICENSE
audioplayer-0.6.dist-info/METADATA
audioplayer-0.6.dist-info/WHEEL
audioplayer-0.6.dist-info/top_level.txt
audioplayer-0.6.dist-info/RECORD
