Metadata-Version: 2.1
Name: audioplayer
Version: 0.6
Summary: audioplayer is a cross platform Python 3 module for playing sounds (mp3, wav, ...)
Home-page: https://github.com/mjbrusso/audioplayer
Author: Marcos Brusso
Author-email: mjbrusso@gmail.com
License: MIT License
Keywords: sound,audioplayer,music,player,game,games,mp3,wav,audio
Platform: UNKNOWN
Classifier: Development Status :: 4 - Beta
Classifier: Programming Language :: Python :: 3
Classifier: Topic :: Multimedia
Classifier: Topic :: Multimedia :: Sound/Audio
Classifier: Topic :: Multimedia :: Sound/Audio :: Players
Classifier: Topic :: Multimedia :: Sound/Audio :: Players :: MP3
Classifier: Intended Audience :: Developers
Classifier: Intended Audience :: Education
Classifier: License :: OSI Approved :: MIT License
Requires-Python: >=3
